retki/__init__.py
retki/compiler.py
retki/language.py
retki/retki-web.py
retki/std.txt
retki/tekstiseikkailukirjasto.txt
retki/tokenutils.py
retki-0.12.1.dist-info/LICENSE
retki-0.12.1.dist-info/METADATA
retki-0.12.1.dist-info/WHEEL
retki-0.12.1.dist-info/entry_points.txt
retki-0.12.1.dist-info/top_level.txt
retki-0.12.1.dist-info/RECORD
