Metadata-Version: 2.1
Name: retki
Version: 0.12.1
Summary: Finnish programming language inspired by Inform 7
Home-page: http://github.com/fergusq/retki
Author: Iikka Hauhio
Author-email: iikka.hauhio@gmail.com
License: GPL
Platform: UNKNOWN
Classifier: Programming Language :: Python :: 3
Requires-Python: >=3
Requires-Dist: voikko
Requires-Dist: suomilog
